examples/deployment_package/__init__.py
examples/deployment_package/deployment.py
ubiops_cli/__init__.py
ubiops_cli/constants.py
ubiops_cli/exceptions.py
ubiops_cli/main.py
ubiops_cli/utils.py
ubiops_cli/version.py
ubiops_cli/complete/__init__.py
ubiops_cli/complete/ubiops-complete.bash
ubiops_cli/complete/ubiops-complete.fish
ubiops_cli/complete/ubiops-complete.zsh
ubiops_cli/gitignorefile/__init__.py
ubiops_cli/gitignorefile/setup.py
ubiops_cli/gitignorefile/gitignorefile/__init__.py
ubiops_cli/gitignorefile/tests/__init__.py
ubiops_cli/gitignorefile/tests/test_cache.py
ubiops_cli/gitignorefile/tests/test_ignore.py
ubiops_cli/gitignorefile/tests/test_ignored.py
ubiops_cli/gitignorefile/tests/test_match.py
ubiops_cli/src/__init__.py
ubiops_cli/src/auth.py
ubiops_cli/src/buckets.py
ubiops_cli/src/completions.py
ubiops_cli/src/config.py
ubiops_cli/src/deployment_revisions.py
ubiops_cli/src/deployment_versions.py
ubiops_cli/src/deployments.py
ubiops_cli/src/environment_builds.py
ubiops_cli/src/environment_revisions.py
ubiops_cli/src/environment_variables.py
ubiops_cli/src/environments.py
ubiops_cli/src/exports.py
ubiops_cli/src/files.py
ubiops_cli/src/imports.py
ubiops_cli/src/instance_type_groups.py
ubiops_cli/src/instance_types.py
ubiops_cli/src/instances.py
ubiops_cli/src/logs.py
ubiops_cli/src/pipeline_versions.py
ubiops_cli/src/pipelines.py
ubiops_cli/src/project_instances.py
ubiops_cli/src/projects.py
ubiops_cli/src/request_schedules.py
ubiops_cli/src/run_local.py
ubiops_cli/src/validation.py
ubiops_cli/src/helpers/__init__.py
ubiops_cli/src/helpers/bucket_helpers.py
ubiops_cli/src/helpers/click_helpers.py
ubiops_cli/src/helpers/deployment_helpers.py
ubiops_cli/src/helpers/environment_helpers.py
ubiops_cli/src/helpers/formatting.py
ubiops_cli/src/helpers/helpers.py
ubiops_cli/src/helpers/instance_helpers.py
ubiops_cli/src/helpers/instance_type_group_helpers.py
ubiops_cli/src/helpers/options.py
ubiops_cli/src/helpers/pipeline_helpers.py
ubiops_cli-2.28.0.dist-info/LICENSE
ubiops_cli-2.28.0.dist-info/METADATA
ubiops_cli-2.28.0.dist-info/WHEEL
ubiops_cli-2.28.0.dist-info/entry_points.txt
ubiops_cli-2.28.0.dist-info/top_level.txt
ubiops_cli-2.28.0.dist-info/RECORD
