Metadata-Version: 2.1
Name: ubiops-cli
Version: 2.28.0
Summary: UbiOps Command Line Interface to interact with the UbiOps API.
Author: UbiOps
License: Apache 2.0
Project-URL: Documentation, https://ubiops.com/docs
Project-URL: Source, https://github.com/UbiOps/command-line-interface.git
Keywords: UbiOps Command Line Interface
Classifier: Development Status :: 3 - Alpha
Classifier: License :: OSI Approved :: Apache Software License
Classifier: Programming Language :: Python :: 3 :: Only
Classifier: Intended Audience :: Developers
Requires-Python: >=3.7
License-File: LICENSE
Requires-Dist: requests>=2.17.3
Requires-Dist: tabulate==0.8.10
Requires-Dist: python-dateutil
Requires-Dist: click<8.2,>=7.0
Requires-Dist: ConfigParser==4.0.2
Requires-Dist: colorama==0.4.3
Requires-Dist: pyyaml
Requires-Dist: ubiops==4.11.0
